napari_nd_annotator-0.3.3.dist-info/RECORD
napari_nd_annotator-0.3.3.dist-info/entry_points.txt
napari_nd_annotator-0.3.3.dist-info/WHEEL
napari_nd_annotator-0.3.3.dist-info/top_level.txt
napari_nd_annotator-0.3.3.dist-info/METADATA
napari_nd_annotator-0.3.3.dist-info/licenses/LICENSE
napari_nd_annotator/__init__.py
napari_nd_annotator/_napari_version.py
napari_nd_annotator/napari.yaml
napari_nd_annotator/_helper_functions.py
napari_nd_annotator/_widgets/__init__.py
napari_nd_annotator/_widgets/projections.py
napari_nd_annotator/_widgets/annotator_module.py
napari_nd_annotator/_widgets/minimal_surface_widget.py
napari_nd_annotator/_widgets/object_list.py
napari_nd_annotator/_widgets/interpolation_widget.py
napari_nd_annotator/_widgets/minimal_contour_widget.py
napari_nd_annotator/_widgets/resources/__init__.py
napari_nd_annotator/_widgets/resources/interpolation/__init__.py
napari_nd_annotator/_widgets/resources/interpolation/interpolate_button.qss
napari_nd_annotator/_widgets/resources/interpolation/interpolate.svg
napari_nd_annotator/_widgets/resources/mc_contour/__init__.py
napari_nd_annotator/_widgets/resources/mc_contour/mc_contour.svg
napari_nd_annotator/_widgets/resources/mc_contour/mc_contour_button.qss
napari_nd_annotator/_widgets/minimal_contour_overlay/__init__.py
napari_nd_annotator/_widgets/minimal_contour_overlay/minimal_contour_overlay.py
napari_nd_annotator/_widgets/minimal_contour_overlay/vispy_minimal_contour_overlay.py
napari_nd_annotator/_widgets/_utils/progress_widget.py
napari_nd_annotator/_widgets/_utils/__init__.py
napari_nd_annotator/_widgets/_utils/callbacks.py
napari_nd_annotator/_widgets/_utils/image_processing_widget.py
napari_nd_annotator/_widgets/_utils/widget_with_layer_list.py
napari_nd_annotator/_widgets/_utils/collapsible_widget.py
napari_nd_annotator/_widgets/_utils/help_dialog.py
napari_nd_annotator/_widgets/_utils/changeable_color_box.py
napari_nd_annotator/_widgets/_utils/blur_slider.py
napari_nd_annotator/_widgets/_utils/symmetric_range_slider.py
napari_nd_annotator/_widgets/_utils/napari_slider.py
napari_nd_annotator/_widgets/_utils/delayed_executor.py
napari_nd_annotator/_widgets/_utils/persistence/__init__.py
