Metadata-Version: 2.4
Name: napari-nD-annotator
Version: 0.3.3
Summary: A toolbox for annotating objects one by one in nD
Author: David Bauer, Jozsef Molnar, Dominik Hirling
Author-email: dbauer@brc.hu
License: BSD-3-Clause
Project-URL: Bug Tracker, https://github.com/bauerdavid/napari-nD-annotator/issues
Project-URL: Documentation, https://github.com/bauerdavid/napari-nD-annotator/blob/main/README.md
Project-URL: Source Code, https://github.com/bauerdavid/napari-nD-annotator
Project-URL: User Support, https://github.com/bauerdavid/napari-nD-annotator/issues
Classifier: Development Status :: 2 - Pre-Alpha
Classifier: Intended Audience :: Developers
Classifier: Framework :: napari
Classifier: Topic :: Software Development :: Testing
Classifier: Programming Language :: C
Classifier: Programming Language :: Cython
Classifier: Programming Language :: Python
Classifier: Programming Language :: Python :: 3
Classifier: Programming Language :: Python :: 3.8
Classifier: Programming Language :: Python :: 3.9
Classifier: Programming Language :: Python :: 3.10
Classifier: Programming Language :: Python :: 3.11
Classifier: Programming Language :: Python :: 3.12
Classifier: Programming Language :: Python :: 3.13
Classifier: Programming Language :: Python :: Implementation :: CPython
Classifier: Operating System :: OS Independent
Classifier: License :: OSI Approved :: BSD License
Requires-Python: >=3.8
License-File: LICENSE
Requires-Dist: numpy
Requires-Dist: magic-class
Requires-Dist: qtpy
Requires-Dist: opencv-python
Requires-Dist: matplotlib
Requires-Dist: napari>=0.4.11
Requires-Dist: scikit-image>=0.19
Requires-Dist: SimpleITK
Provides-Extra: testing
Requires-Dist: tox; extra == "testing"
Requires-Dist: pytest; extra == "testing"
Requires-Dist: pytest-cov; extra == "testing"
Requires-Dist: pytest-qt; extra == "testing"
Requires-Dist: napari; extra == "testing"
Requires-Dist: pyqt5; extra == "testing"
Requires-Dist: numpy; extra == "testing"
Provides-Extra: bbox
Requires-Dist: napari-bbox; extra == "bbox"
Provides-Extra: ms
Requires-Dist: minimal-surface; extra == "ms"
Provides-Extra: all
Requires-Dist: napari-bbox; extra == "all"
Requires-Dist: minimal-surface; extra == "all"
Dynamic: license-file
